{
	"configurations" : 
	[
		{
			"directories" : 
			[
				{
					"build" : ".",
					"childIndexes" : 
					[
						1,
						2
					],
					"jsonFile" : "directory-.-Debug-f5ebdc15457944623624.json",
					"minimumCMakeVersion" : 
					{
						"string" : "3.2"
					},
					"projectIndex" : 0,
					"source" : ".",
					"targetIndexes" : 
					[
						2
					]
				},
				{
					"build" : "example",
					"jsonFile" : "directory-example-Debug-b6fca4a6d0a37c6ae6b9.json",
					"minimumCMakeVersion" : 
					{
						"string" : "3.2"
					},
					"parentIndex" : 0,
					"projectIndex" : 0,
					"source" : "example",
					"targetIndexes" : 
					[
						1
					]
				},
				{
					"build" : "example/test",
					"jsonFile" : "directory-example.test-Debug-e272dbd0dbbc608d7bcd.json",
					"minimumCMakeVersion" : 
					{
						"string" : "3.2"
					},
					"parentIndex" : 0,
					"projectIndex" : 0,
					"source" : "example/test",
					"targetIndexes" : 
					[
						0
					]
				}
			],
			"name" : "Debug",
			"projects" : 
			[
				{
					"directoryIndexes" : 
					[
						0,
						1,
						2
					],
					"name" : "YUtil",
					"targetIndexes" : 
					[
						0,
						1,
						2
					]
				}
			],
			"targets" : 
			[
				{
					"directoryIndex" : 2,
					"id" : "bbt_timer_test::@d7ce33078a1c01a78c3e",
					"jsonFile" : "target-bbt_timer_test-Debug-5874713cc8e05de9672c.json",
					"name" : "bbt_timer_test",
					"projectIndex" : 0
				},
				{
					"directoryIndex" : 1,
					"id" : "fileutil_test::@70983d692f648185febe",
					"jsonFile" : "target-fileutil_test-Debug-4c5e56b804ad2590aa4c.json",
					"name" : "fileutil_test",
					"projectIndex" : 0
				},
				{
					"directoryIndex" : 0,
					"id" : "ybbt::@6890427a1f51a3e7e1df",
					"jsonFile" : "target-ybbt-Debug-15ec9e1ef5995c5c0c0c.json",
					"name" : "ybbt",
					"projectIndex" : 0
				}
			]
		}
	],
	"kind" : "codemodel",
	"paths" : 
	{
		"build" : "/home/yqm/Git/biangbiangtools/build",
		"source" : "/home/yqm/Git/biangbiangtools"
	},
	"version" : 
	{
		"major" : 2,
		"minor" : 3
	}
}
